easypipe/__init__.py
easypipe/face.py
easypipe/hands.py
easypipe/source.py
easypipe/utils.py
easypipe-0.0.3.dist-info/LICENSE
easypipe-0.0.3.dist-info/METADATA
easypipe-0.0.3.dist-info/WHEEL
easypipe-0.0.3.dist-info/top_level.txt
easypipe-0.0.3.dist-info/RECORD
