Metadata-Version: 2.1
Name: easypipe
Version: 0.0.3
Summary: EasyPipe is a simple tool for developers to build ML applications.
Home-page: https://github.com/kalmufti/easypipe
Author: Khalid Almufti
Author-email: almufti.khalid@gmail.com
License: Apache 2.0
Project-URL: Bug Tracker, https://github.com/kalmufti/easypipe/issues
Keywords: mediapipe
Platform: UNKNOWN
Classifier: Development Status :: 1 - Planning
Classifier: Intended Audience :: Developers
Classifier: Intended Audience :: Education
Classifier: Intended Audience :: Science/Research
Classifier: Programming Language :: Python :: 3
Classifier: Programming Language :: Python :: 3.7
Classifier: Programming Language :: Python :: 3.8
Classifier: Programming Language :: Python :: 3.9
Classifier: License :: OSI Approved :: Apache Software License
Classifier: Operating System :: OS Independent
Classifier: Topic :: Scientific/Engineering
Classifier: Topic :: Scientific/Engineering :: Artificial Intelligence
Classifier: Topic :: Software Development
Classifier: Topic :: Software Development :: Libraries
Classifier: Topic :: Software Development :: Libraries :: Python Modules
Requires-Python: >=3.6
License-File: LICENSE
Requires-Dist: mediapipe
Requires-Dist: opencv-python (>=4.5)
Provides-Extra: dev
Requires-Dist: pytest (>=6.2) ; extra == 'dev'
